littlechunks/__init__.py
littlechunks/__main__.py
littlechunks/csv.py
littlechunks/utils.py
littlechunks/data/chunk_0.csv
littlechunks/data/chunk_1.csv
littlechunks/data/chunk_2.csv
littlechunks/data/test_file.csv
littlechunks-0.0.1.dist-info/LICENSE
littlechunks-0.0.1.dist-info/METADATA
littlechunks-0.0.1.dist-info/WHEEL
littlechunks-0.0.1.dist-info/entry_points.txt
littlechunks-0.0.1.dist-info/top_level.txt
littlechunks-0.0.1.dist-info/RECORD
